moudle/__init__.py
moudle/core.py
ragcheckerzhongshuiv2-0.0.1.dist-info/LICENSE
ragcheckerzhongshuiv2-0.0.1.dist-info/METADATA
ragcheckerzhongshuiv2-0.0.1.dist-info/WHEEL
ragcheckerzhongshuiv2-0.0.1.dist-info/top_level.txt
ragcheckerzhongshuiv2-0.0.1.dist-info/RECORD
